MANIFEST.in
README.md
setup.py
hotweb_cli/__init__.py
hotweb_cli/cli.py
hotweb_cli/exceptions.py
hotweb_cli/utils.py
hotweb_cli.egg-info/PKG-INFO
hotweb_cli.egg-info/SOURCES.txt
hotweb_cli.egg-info/dependency_links.txt
hotweb_cli.egg-info/entry_points.txt
hotweb_cli.egg-info/top_level.txt
hotweb_cli/migrations/__init__.py
hotweb_cli/migrations/migration.py
hotweb_cli/models/__init__.py
hotweb_cli/models/bafana.py
hotweb_cli/models/cash.py
hotweb_cli/models/hadson.py
hotweb_cli/models/haduser.py
hotweb_cli/models/model_skeleton.py
hotweb_cli/models/models.py
hotweb_cli/models/nan.py
hotweb_cli/models/testd.py
hotweb_cli/models/users.py