Metadata-Version: 2.1
Name: hotweb-cli
Version: 0.0.121
Summary: hotweb_cli, a cli tool for hotweb framework
Author: Real Manlow,aka ManlowCharumbira
Author-email: realmanlow20@gmail.com
License: MIT
Keywords: hotweb python-web-framework python web framework fast light secure
